{
  "source": "dfs",
  "type_reps": 2,
  "teamwod": false,
  "rest_between": true,
  "buy_in": {
    "exist": false,
    "movement": null,
    "count": null,
    "quantity": null,
    "weight": null
  },
  "type_rep_1": {
    "type": "EMOM",
    "round": 8,
    "token": 2,
    "emom_cycle_length": 5,
    "onoff": false,
    "on_duration": null,
    "off_duration": null,
    "time_cap": 16,
    "rest": true,
    "movements": [
      {
        "movement": "rope climb",
        "ladder": false,
        "count": 1,
        "quantity": "rep",
        "weight": null,
        "increase": false,
        "increase_every": null,
        "increase_quantity": null,
        "increase_unit_count": null,
        "increase_unit_type": null
      },
      {
        "movement": "bar facing burpees",
        "ladder": false,
        "count": 3,
        "quantity": "rep",
        "weight": null,
        "increase": false,
        "increase_every": null,
        "increase_quantity": null,
        "increase_unit_count": null,
        "increase_unit_type": null
      },
      {
        "movement": "power snatch",
        "ladder": false,
        "count": 5,
        "quantity": "rep",
        "weight": null,
        "increase": false,
        "increase_every": null,
        "increase_quantity": null,
        "increase_unit_count": null,
        "increase_unit_type": null
      },
      {
        "movement": "bar facing burpees",
        "ladder": false,
        "count": 3,
        "quantity": "rep",
        "weight": null,
        "increase": false,
        "increase_every": null,
        "increase_quantity": null,
        "increase_unit_count": null,
        "increase_unit_type": null
      },
      {
        "movement": "bike",
        "ladder": false,
        "count": -1,
        "quantity": "cal",
        "weight": null,
        "increase": false,
        "increase_every": null,
        "increase_quantity": null,
        "increase_unit_count": null,
        "increase_unit_type": null
      }
    ]
  },
  "type_rep_2": {
    "type": "For Time",
    "round": null,
    "token": null,
    "emom_cycle_length": null,
    "onoff": null,
    "on_duration": null,
    "off_duration": null,
    "time_cap": 10,
    "rest": false,
    "movements": [
      {
        "movement": "push press",
        "ladder": false,
        "count": 25,
        "quantity": "rep",
        "weight": null,
        "increase": false,
        "increase_every": null,
        "increase_quantity": null,
        "increase_unit_count": null,
        "increase_unit_type": null
      },
      {
        "movement": "kettlebell swing",
        "ladder": false,
        "count": 50,
        "quantity": "rep",
        "weight": null,
        "increase": false,
        "increase_every": null,
        "increase_quantity": null,
        "increase_unit_count": null,
        "increase_unit_type": null
      },
      {
        "movement": "push press",
        "ladder": false,
        "count": 25,
        "quantity": "rep",
        "weight": null,
        "increase": false,
        "increase_every": null,
        "increase_quantity": null,
        "increase_unit_count": null,
        "increase_unit_type": null
      }
    ]
  }
}