{
  "source": "calgary",
  "type_reps": 1,
  "teamwod": false,
  "rest_between": false,
  "buy_in": {
    "exist": false,
    "movement": null,
    "count": null,
    "quantity": null,
    "weight": null
  },
  "type_rep_1": {
    "type": "AMRAP",
    "round": null,
    "token": null,
    "emom_cycle_length": null,
    "onoff": null,
    "on_duration": null,
    "off_duration": null,
    "time_cap": 10,
    "rest": false,
    "movements": [
      {
        "movement": "walking lunge",
        "ladder": false,
        "count": 20,
        "quantity": "rep",
        "weight": null,
        "increase": false
      },
      {
        "movement": "wall walk",
        "ladder": false,
        "count": 2,
        "quantity": "rep",
        "weight": null,
        "increase": false
      },
      {
        "movement": "sit-up",
        "ladder": false,
        "count": 20,
        "quantity": "rep",
        "weight": null,
        "increase": false
      },
      {
        "movement": "wall walk",
        "ladder": false,
        "count": 2,
        "quantity": "rep",
        "weight": null,
        "increase": false
      }
    ]
  }
}