{
  "source": "tam",
  "type_reps": 2,
  "teamwod": false,
  "rest_between": true,
  "buy_in": {
    "exist": false,
    "movement": null,
    "count": null,
    "quantity": null,
    "weight": null
  },
  "buy_out": {
    "exist": false,
    "movement": null,
    "count": null,
    "quantity": null,
    "weight": null
  },
  "type_rep_1": {
    "type": "AMRAP",
    "round": null,
    "token": null,
    "emom_cycle_length": null,
    "onoff": null,
    "on_duration": null,
    "off_duration": null,
    "time_cap": 10,
    "rest": false,
    "movements": [
      {
        "movement": "single unders",
        "ladder": true,
        "count": 25,
        "quantity": "rep",
        "weight": null,
        "increase": true,
        "increase_every": 25,
        "increase_quantity": "rep",
        "increase_unit_count": 1,
        "increase_unit_type": "round"
      },
      {
        "movement": "strict pull up",
        "ladder": true,
        "count": 3,
        "quantity": "rep",
        "weight": null,
        "increase": true,
        "increase_every": 3,
        "increase_quantity": "rep",
        "increase_unit_count": 1,
        "increase_unit_type": "round"
      }
    ]
  },
  "type_rep_2": {
    "type": "AMRAP",
    "round": null,
    "token": null,
    "emom_cycle_length": null,
    "onoff": null,
    "on_duration": null,
    "off_duration": null,
    "time_cap": 10,
    "rest": false,
    "movements": [
      {
        "movement": "row",
        "ladder": true,
        "count": 3,
        "quantity": "cal",
        "weight": null,
        "increase": true,
        "increase_every": 3,
        "increase_quantity": "cal",
        "increase_unit_count": 1,
        "increase_unit_type": "round"
      },
      {
        "movement": "strict handstand push-up",
        "ladder": true,
        "count": 3,
        "quantity": "rep",
        "weight": null,
        "increase": true,
        "increase_every": 3,
        "increase_quantity": "rep",
        "increase_unit_count": 1,
        "increase_unit_type": "round"
      }
    ]
  }
}